setup.cfg
setup.py
cave_miner/__init__.py
cave_miner/inject.py
cave_miner/main.py
cave_miner/search.py
cave_miner/tests.py
cave_miner/utils.py
cave_miner.egg-info/PKG-INFO
cave_miner.egg-info/SOURCES.txt
cave_miner.egg-info/dependency_links.txt
cave_miner.egg-info/entry_points.txt
cave_miner.egg-info/requires.txt
cave_miner.egg-info/top_level.txt
cave_miner/formats/__init__.py
cave_miner/formats/elf.py
cave_miner/formats/mach_o.py
cave_miner/formats/microsoft_pe.py