Metadata-Version: 1.0
Name: cave-miner
Version: 1.7
Summary: Search for code cave in all binaries
Home-page: https://github.com/Antonin-Deniau/cave_miner
Author: DENIAU Antonin
Author-email: antonin.deniau@protonmail.com
License: UNKNOWN
Keywords: code,cave,codecave,macho,mach-o,elf,pe
Platform: UNKNOWN
